[{"PartyName":"MAURICIO RODRÍGUEZ-IZQUIERDO GARCÍA","PartyIdentification":"31667425J"},{"PartyName":"MAURICIO RODRÍGUEZ-IZQUIERDO GARCÍA","PartyIdentification":"31667425J"},{"PartyName":"Noelia Herrera Beltrán","PartyIdentification":"31723596H"},{"PartyName":"EMELL EVENTOS S.L.","PartyIdentification":"B72285240"},{"PartyName":"ASOCIACIÓN RECREATIVO CULTURAL SUR PIPES BAND","PartyIdentification":"G05293030"},{"PartyName":"THE ROCK AND ROLL CLUB","PartyIdentification":"G11932225"},{"PartyName":"ERNESTO J. TOBOSO SUÁREZ","PartyIdentification":"75815142N"},{"PartyName":"MARIA ISABEL AVILA TOLEDO","PartyIdentification":"75766568Z"},{"PartyName":"MARÍA ISABEL ÁLVAREZ GONZÁLEZ, S.L.N.E.","PartyIdentification":"B11834702"},{"PartyName":"BALTEUS ARQUEOLOGÍA Y PATRIMONIO S.L.N.E.","PartyIdentification":"B72125511"},{"PartyName":"PAVEL HOREJSI","PartyIdentification":"CZ7008310485"},{"PartyName":"CARLOS MANUEL FLORES GARCÍA (F&R ASESORIA PSICOLÓGICA)","PartyIdentification":"30237785F"},{"PartyName":"SEPTIMA REFORMAS Y GESTION DE EDIFICIOS S.L.","PartyIdentification":"B11975844"},{"PartyName":"AFC CONSTRUCCIONES Y CONTRATAS S.L.","PartyIdentification":"B18854166"},{"PartyName":"PORTICOR INNOVACIONES, S.L.","PartyIdentification":"B91221705"},{"PartyName":"SYRUP SL","PartyIdentification":"B67671255"},{"PartyName":"TOWER BRIDGE S.L.","PartyIdentification":"B80029895"}]